{
  "last_run": "2026-01-14T10:11:39.103395+00:00",
  "status": "success",
  "statistics": {
    "total_articles": 1468,
    "trending_topics": 10,
    "categories": {
      "Constitutional & Legal": 184,
      "Infrastructure & Transport": 47,
      "Economic Policy": 797,
      "Trade & Industry": 54,
      "Policy News": 119,
      "Governance & Administration": 74,
      "Foreign Policy": 9,
      "Politics": 31,
      "Healthcare Policy": 28,
      "Technology Policy": 46,
      "Defence & Security": 25,
      "Consumer Affairs": 5,
      "Education Policy": 11,
      "Environmental Policy": 10,
      "Agricultural Policy": 6,
      "Social Policy": 14,
      "Energy Policy": 8
    },
    "priorities": {
      "critical": 44,
      "high": 176,
      "medium": 1248
    }
  }
}