{
  "last_run": "2026-02-23T07:23:28.247774+00:00",
  "status": "success",
  "statistics": {
    "total_articles": 822,
    "trending_topics": 8,
    "categories": {
      "Finance": 109,
      "Legal": 74,
      "Foreign": 82,
      "Trade": 178,
      "Politics": 87,
      "Infrastructure": 34,
      "Defence": 21,
      "Environment": 16,
      "Governance": 12,
      "Data Privacy": 2,
      "Urban": 17,
      "Health": 13,
      "Energy": 29,
      "Welfare": 14,
      "Telecom": 16,
      "DeepTech": 40,
      "Fintech": 56,
      "Education": 17,
      "Agriculture": 5
    },
    "priorities": {
      "critical": 24,
      "high": 99,
      "medium": 699
    }
  }
}