{
  "last_run": "2026-03-03T11:17:01.975784+00:00",
  "status": "success",
  "statistics": {
    "total_articles": 808,
    "trending_topics": 6,
    "categories": {
      "Legal": 106,
      "Foreign": 224,
      "Technology": 55,
      "Politics": 38,
      "Finance": 125,
      "Governance": 73,
      "Civil Liberties": 28,
      "Welfare": 5,
      "Trade": 40,
      "Infrastructure": 20,
      "Agriculture": 4,
      "Health": 9,
      "Energy": 28,
      "Environment": 23,
      "Labour": 6,
      "Telecom": 8,
      "Education": 4,
      "Defence": 10,
      "Fintech": 1,
      "DeepTech": 1
    },
    "priorities": {
      "critical": 24,
      "high": 97,
      "medium": 687
    }
  }
}