{
  "last_run": "2026-01-17T16:29:40.137380+00:00",
  "status": "success",
  "statistics": {
    "total_articles": 1806,
    "trending_topics": 8,
    "categories": {
      "Constitutional & Legal": 237,
      "Governance & Administration": 286,
      "Trade & Industry": 92,
      "Policy News": 118,
      "Economic Policy": 782,
      "Foreign Policy": 14,
      "Environmental Policy": 27,
      "Social Policy": 10,
      "Consumer Affairs": 24,
      "Technology Policy": 38,
      "Education Policy": 10,
      "Defence & Security": 29,
      "Infrastructure & Transport": 45,
      "Politics": 53,
      "Healthcare Policy": 27,
      "Energy Policy": 7,
      "Agricultural Policy": 7
    },
    "priorities": {
      "critical": 56,
      "high": 257,
      "medium": 1493
    }
  }
}